[
    {
        "Name": "LOC_NAMED_LAKE_AGUA_VERMELHA_NAME",
        "NamedLakeType": "NAMED_LAKE_AGUA_VERMELHA"
    },
    {
        "Name": "LOC_NAMED_LAKE_ALTYEVATNET_NAME",
        "NamedLakeType": "NAMED_LAKE_ALTYEVATNET"
    },
    {
        "Name": "LOC_NAMED_LAKE_AMANZAMNYAMA_NAME",
        "NamedLakeType": "NAMED_LAKE_AMANZAMNYAMA"
    },
    {
        "Name": "LOC_NAMED_LAKE_ARAL_SEA_NAME",
        "NamedLakeType": "NAMED_LAKE_ARAL_SEA"
    },
    {
        "Name": "LOC_NAMED_LAKE_BAENGNOKDAM_NAME",
        "NamedLakeType": "NAMED_LAKE_BAENGNOKDAM"
    },
    {
        "Name": "LOC_NAMED_LAKE_BAKHTEGAN_LAKE_NAME",
        "NamedLakeType": "NAMED_LAKE_BAKHTEGAN_LAKE"
    },
    {
        "Name": "LOC_NAMED_LAKE_BASSENTHWAITE_LAKE_NAME",
        "NamedLakeType": "NAMED_LAKE_BASSENTHWAITE_LAKE"
    },
    {
        "Name": "LOC_NAMED_LAKE_BLASJO_NAME",
        "NamedLakeType": "NAMED_LAKE_BLASJO"
    },
    {
        "Name": "LOC_NAMED_LAKE_BOEUNG_KAK_NAME",
        "NamedLakeType": "NAMED_LAKE_BOEUNG_KAK"
    },
    {
        "Name": "LOC_NAMED_LAKE_BOURGET_LAKE_NAME",
        "NamedLakeType": "NAMED_LAKE_BOURGET_LAKE"
    },
    {
        "Name": "LOC_NAMED_LAKE_BUDI_LAKE_NAME",
        "NamedLakeType": "NAMED_LAKE_BUDI_LAKE"
    },
    {
        "Name": "LOC_NAMED_LAKE_BUWELNO_LAKE_NAME",
        "NamedLakeType": "NAMED_LAKE_BUWELNO_LAKE"
    },
    {
        "Name": "LOC_NAMED_LAKE_CABURGUA_LAKE_NAME",
        "NamedLakeType": "NAMED_LAKE_CABURGUA_LAKE"
    },
    {
        "Name": "LOC_NAMED_LAKE_CHAO_LAKE_NAME",
        "NamedLakeType": "NAMED_LAKE_CHAO_LAKE"
    },
    {
        "Name": "LOC_NAMED_LAKE_CHINCHAYQUCHA_NAME",
        "NamedLakeType": "NAMED_LAKE_CHINCHAYQUCHA"
    },
    {
        "Name": "LOC_NAMED_LAKE_CONISON_LAKE_NAME",
        "NamedLakeType": "NAMED_LAKE_CONISON_LAKE"
    },
    {
        "Name": "LOC_NAMED_LAKE_DABIE_LAKE_NAME",
        "NamedLakeType": "NAMED_LAKE_DABIE_LAKE"
    },
    {
        "Name": "LOC_NAMED_LAKE_DAL_LAKE_NAME",
        "NamedLakeType": "NAMED_LAKE_DAL_LAKE"
    },
    {
        "Name": "LOC_NAMED_LAKE_DERWENTWATER_LAKE_NAME",
        "NamedLakeType": "NAMED_LAKE_DERWENTWATER_LAKE"
    },
    {
        "Name": "LOC_NAMED_LAKE_DIPOR_BIL_NAME",
        "NamedLakeType": "NAMED_LAKE_DIPOR_BIL"
    },
    {
        "Name": "LOC_NAMED_LAKE_DOBSKIE_LAKE_NAME",
        "NamedLakeType": "NAMED_LAKE_DOBSKIE_LAKE"
    },
    {
        "Name": "LOC_NAMED_LAKE_DOIRAN_LAKE_NAME",
        "NamedLakeType": "NAMED_LAKE_DOIRAN_LAKE"
    },
    {
        "Name": "LOC_NAMED_LAKE_DONGTING_LAKE_NAME",
        "NamedLakeType": "NAMED_LAKE_DONGTING_LAKE"
    },
    {
        "Name": "LOC_NAMED_LAKE_EL_BRICIAL_NAME",
        "NamedLakeType": "NAMED_LAKE_EL_BRICIAL"
    },
    {
        "Name": "LOC_NAMED_LAKE_FELDGES_LAKE_NAME",
        "NamedLakeType": "NAMED_LAKE_FELDGES_LAKE"
    },
    {
        "Name": "LOC_NAMED_LAKE_FEMUNDEN_NAME",
        "NamedLakeType": "NAMED_LAKE_FEMUNDEN"
    },
    {
        "Name": "LOC_NAMED_LAKE_FUCINE_LAKE_NAME",
        "NamedLakeType": "NAMED_LAKE_FUCINE_LAKE"
    },
    {
        "Name": "LOC_NAMED_LAKE_GALLETU_LAKE_NAME",
        "NamedLakeType": "NAMED_LAKE_GALLETU_LAKE"
    },
    {
        "Name": "LOC_NAMED_LAKE_GREAT_BEAR_LAKE_NAME",
        "NamedLakeType": "NAMED_LAKE_GREAT_BEAR_LAKE"
    },
    {
        "Name": "LOC_NAMED_LAKE_GREAT_BITTER_LAKE_NAME",
        "NamedLakeType": "NAMED_LAKE_GREAT_BITTER_LAKE"
    },
    {
        "Name": "LOC_NAMED_LAKE_GREAT_SALT_LAKE_NAME",
        "NamedLakeType": "NAMED_LAKE_GREAT_SALT_LAKE"
    },
    {
        "Name": "LOC_NAMED_LAKE_GREAT_SLAVE_LAKE_NAME",
        "NamedLakeType": "NAMED_LAKE_GREAT_SLAVE_LAKE"
    },
    {
        "Name": "LOC_NAMED_LAKE_GREENLEE_LOUGH_NAME",
        "NamedLakeType": "NAMED_LAKE_GREENLEE_LOUGH"
    },
    {
        "Name": "LOC_NAMED_LAKE_GUARAPIRANGA_NAME",
        "NamedLakeType": "NAMED_LAKE_GUARAPIRANGA"
    },
    {
        "Name": "LOC_NAMED_LAKE_HAMUN_LAKE_NAME",
        "NamedLakeType": "NAMED_LAKE_HAMUN_LAKE"
    },
    {
        "Name": "LOC_NAMED_LAKE_HAWR_AS_SADIYAH_NAME",
        "NamedLakeType": "NAMED_LAKE_HAWR_AS_SADIYAH"
    },
    {
        "Name": "LOC_NAMED_LAKE_HEAVEN_LAKE_NAME",
        "NamedLakeType": "NAMED_LAKE_HEAVEN_LAKE"
    },
    {
        "Name": "LOC_NAMED_LAKE_HJALMAREN_NAME",
        "NamedLakeType": "NAMED_LAKE_HJALMAREN"
    },
    {
        "Name": "LOC_NAMED_LAKE_HONGZE_LAKE_NAME",
        "NamedLakeType": "NAMED_LAKE_HONGZE_LAKE"
    },
    {
        "Name": "LOC_NAMED_LAKE_HORNINDALSVATNET_NAME",
        "NamedLakeType": "NAMED_LAKE_HORNINDALSVATNET"
    },
    {
        "Name": "LOC_NAMED_LAKE_HULUN_LAKE_NAME",
        "NamedLakeType": "NAMED_LAKE_HULUN_LAKE"
    },
    {
        "Name": "LOC_NAMED_LAKE_ICHKEUL_LAKE_NAME",
        "NamedLakeType": "NAMED_LAKE_ICHKEUL_LAKE"
    },
    {
        "Name": "LOC_NAMED_LAKE_ILIAMNA_LAKE_NAME",
        "NamedLakeType": "NAMED_LAKE_ILIAMNA_LAKE"
    },
    {
        "Name": "LOC_NAMED_LAKE_ISSYK_KUL_LAKE_NAME",
        "NamedLakeType": "NAMED_LAKE_ISSYK_KUL_LAKE"
    },
    {
        "Name": "LOC_NAMED_LAKE_KARTSAKHI_LAKE_NAME",
        "NamedLakeType": "NAMED_LAKE_KARTSAKHI_LAKE"
    },
    {
        "Name": "LOC_NAMED_LAKE_KHAR_US_LAKE_NAME",
        "NamedLakeType": "NAMED_LAKE_KHAR_US_LAKE"
    },
    {
        "Name": "LOC_NAMED_LAKE_KHOVSGOL_LAKE_NAME",
        "NamedLakeType": "NAMED_LAKE_KHOVSGOL_LAKE"
    },
    {
        "Name": "LOC_NAMED_LAKE_KHYARGAS_LAKE_NAME",
        "NamedLakeType": "NAMED_LAKE_KHYARGAS_LAKE"
    },
    {
        "Name": "LOC_NAMED_LAKE_KILUNDA_LAKE_NAME",
        "NamedLakeType": "NAMED_LAKE_KILUNDA_LAKE"
    },
    {
        "Name": "LOC_NAMED_LAKE_KOLLERU_LAKE_NAME",
        "NamedLakeType": "NAMED_LAKE_KOLLERU_LAKE"
    },
    {
        "Name": "LOC_NAMED_LAKE_KONIGSSEE_NAME",
        "NamedLakeType": "NAMED_LAKE_KONIGSSEE"
    },
    {
        "Name": "LOC_NAMED_LAKE_KOSI_LAKE_NAME",
        "NamedLakeType": "NAMED_LAKE_KOSI_LAKE"
    },
    {
        "Name": "LOC_NAMED_LAKE_LAC_DE_GRAND_LIEU_NAME",
        "NamedLakeType": "NAMED_LAKE_LAC_DE_GRAND_LIEU"
    },
    {
        "Name": "LOC_NAMED_LAKE_LAGOA_DOS_PATOS_NAME",
        "NamedLakeType": "NAMED_LAKE_LAGOA_DOS_PATOS"
    },
    {
        "Name": "LOC_NAMED_LAKE_LAGUNA_DE_BAY_NAME",
        "NamedLakeType": "NAMED_LAKE_LAGUNA_DE_BAY"
    },
    {
        "Name": "LOC_NAMED_LAKE_LAKE_ADAPASKAW_NAME",
        "NamedLakeType": "NAMED_LAKE_LAKE_ADAPASKAW"
    },
    {
        "Name": "LOC_NAMED_LAKE_LAKE_AIGUEBELETTE_NAME",
        "NamedLakeType": "NAMED_LAKE_LAKE_AIGUEBELETTE"
    },
    {
        "Name": "LOC_NAMED_LAKE_LAKE_ALAKOL_NAME",
        "NamedLakeType": "NAMED_LAKE_LAKE_ALAKOL"
    },
    {
        "Name": "LOC_NAMED_LAKE_LAKE_ALBERT_NAME",
        "NamedLakeType": "NAMED_LAKE_LAKE_ALBERT"
    },
    {
        "Name": "LOC_NAMED_LAKE_LAKE_AMADEUS_NAME",
        "NamedLakeType": "NAMED_LAKE_LAKE_AMADEUS"
    },
    {
        "Name": "LOC_NAMED_LAKE_LAKE_AMMER_NAME",
        "NamedLakeType": "NAMED_LAKE_LAKE_AMMER"
    },
    {
        "Name": "LOC_NAMED_LAKE_LAKE_ANNECY_NAME",
        "NamedLakeType": "NAMED_LAKE_LAKE_ANNECY"
    },
    {
        "Name": "LOC_NAMED_LAKE_LAKE_ANTOGO_NAME",
        "NamedLakeType": "NAMED_LAKE_LAKE_ANTOGO"
    },
    {
        "Name": "LOC_NAMED_LAKE_LAKE_AOUGOUNDOU",
        "NamedLakeType": "NAMED_LAKE_LAKE_AOUGOUNDOU"
    },
    {
        "Name": "LOC_NAMED_LAKE_LAKE_ATITLAN_NAME",
        "NamedLakeType": "NAMED_LAKE_LAKE_ATITLAN"
    },
    {
        "Name": "LOC_NAMED_LAKE_LAKE_BAIKAL_NAME",
        "NamedLakeType": "NAMED_LAKE_LAKE_BAIKAL"
    },
    {
        "Name": "LOC_NAMED_LAKE_LAKE_BALATON_NAME",
        "NamedLakeType": "NAMED_LAKE_LAKE_BALATON"
    },
    {
        "Name": "LOC_NAMED_LAKE_LAKE_BALKHASH_NAME",
        "NamedLakeType": "NAMED_LAKE_LAKE_BALKHASH"
    },
    {
        "Name": "LOC_NAMED_LAKE_LAKE_BANGWEULU_NAME",
        "NamedLakeType": "NAMED_LAKE_LAKE_BANGWEULU"
    },
    {
        "Name": "LOC_NAMED_LAKE_LAKE_BARDAWIL_NAME",
        "NamedLakeType": "NAMED_LAKE_LAKE_BARDAWIL"
    },
    {
        "Name": "LOC_NAMED_LAKE_LAKE_BENACUS_NAME",
        "NamedLakeType": "NAMED_LAKE_LAKE_BENACUS"
    },
    {
        "Name": "LOC_NAMED_LAKE_LAKE_BEYSEHIR_NAME",
        "NamedLakeType": "NAMED_LAKE_LAKE_BEYSEHIR"
    },
    {
        "Name": "LOC_NAMED_LAKE_LAKE_BIWA_NAME",
        "NamedLakeType": "NAMED_LAKE_LAKE_BIWA"
    },
    {
        "Name": "LOC_NAMED_LAKE_LAKE_BOLSENA_NAME",
        "NamedLakeType": "NAMED_LAKE_LAKE_BOLSENA"
    },
    {
        "Name": "LOC_NAMED_LAKE_LAKE_BRACCIANO_NAME",
        "NamedLakeType": "NAMED_LAKE_LAKE_BRACCIANO"
    },
    {
        "Name": "LOC_NAMED_LAKE_LAKE_BUJO_NAME",
        "NamedLakeType": "NAMED_LAKE_LAKE_BUJO"
    },
    {
        "Name": "LOC_NAMED_LAKE_LAKE_BURDUR_NAME",
        "NamedLakeType": "NAMED_LAKE_LAKE_BURDUR"
    },
    {
        "Name": "LOC_NAMED_LAKE_LAKE_CARNEGIE_NAME",
        "NamedLakeType": "NAMED_LAKE_LAKE_CARNEGIE"
    },
    {
        "Name": "LOC_NAMED_LAKE_LAKE_CHALCO_NAME",
        "NamedLakeType": "NAMED_LAKE_LAKE_CHALCO"
    },
    {
        "Name": "LOC_NAMED_LAKE_LAKE_CHAMPLAIN_NAME",
        "NamedLakeType": "NAMED_LAKE_LAKE_CHAMPLAIN"
    },
    {
        "Name": "LOC_NAMED_LAKE_LAKE_CHIEMSEE_NAME",
        "NamedLakeType": "NAMED_LAKE_LAKE_CHIEMSEE"
    },
    {
        "Name": "LOC_NAMED_LAKE_LAKE_CHON_NAME",
        "NamedLakeType": "NAMED_LAKE_LAKE_CHON"
    },
    {
        "Name": "LOC_NAMED_LAKE_LAKE_CONSTANCE_NAME",
        "NamedLakeType": "NAMED_LAKE_LAKE_CONSTANCE"
    },
    {
        "Name": "LOC_NAMED_LAKE_LAKE_COPAIS_NAME",
        "NamedLakeType": "NAMED_LAKE_LAKE_COPAIS"
    },
    {
        "Name": "LOC_NAMED_LAKE_LAKE_DEBO_NAME",
        "NamedLakeType": "NAMED_LAKE_LAKE_DEBO"
    },
    {
        "Name": "LOC_NAMED_LAKE_LAKE_DISAPPOINTMENT_NAME",
        "NamedLakeType": "NAMED_LAKE_LAKE_DISAPPOINTMENT"
    },
    {
        "Name": "LOC_NAMED_LAKE_LAKE_EGIRDIR_NAME",
        "NamedLakeType": "NAMED_LAKE_LAKE_EGIRDIR"
    },
    {
        "Name": "LOC_NAMED_LAKE_LAKE_ENOL_NAME",
        "NamedLakeType": "NAMED_LAKE_LAKE_ENOL"
    },
    {
        "Name": "LOC_NAMED_LAKE_LAKE_ERCINA_NAME",
        "NamedLakeType": "NAMED_LAKE_LAKE_ERCINA"
    },
    {
        "Name": "LOC_NAMED_LAKE_LAKE_ERIE_NAME",
        "NamedLakeType": "NAMED_LAKE_LAKE_ERIE"
    },
    {
        "Name": "LOC_NAMED_LAKE_LAKE_EYRE_NAME",
        "NamedLakeType": "NAMED_LAKE_LAKE_EYRE"
    },
    {
        "Name": "LOC_NAMED_LAKE_LAKE_FAGUIBINE_NAME",
        "NamedLakeType": "NAMED_LAKE_LAKE_FAGUIBINE"
    },
    {
        "Name": "LOC_NAMED_LAKE_LAKE_FERTO_NAME",
        "NamedLakeType": "NAMED_LAKE_LAKE_FERTO"
    },
    {
        "Name": "LOC_NAMED_LAKE_LAKE_FROME_NAME",
        "NamedLakeType": "NAMED_LAKE_LAKE_FROME"
    },
    {
        "Name": "LOC_NAMED_LAKE_LAKE_GENEVA_NAME",
        "NamedLakeType": "NAMED_LAKE_LAKE_GENEVA"
    },
    {
        "Name": "LOC_NAMED_LAKE_LAKE_GOPLO_NAME",
        "NamedLakeType": "NAMED_LAKE_LAKE_GOPLO"
    },
    {
        "Name": "LOC_NAMED_LAKE_LAKE_GREVELINGEN_NAME",
        "NamedLakeType": "NAMED_LAKE_LAKE_GREVELINGEN"
    },
    {
        "Name": "LOC_NAMED_LAKE_LAKE_HABBANIYAH_NAME",
        "NamedLakeType": "NAMED_LAKE_LAKE_HABBANIYAH"
    },
    {
        "Name": "LOC_NAMED_LAKE_LAKE_HAMMAR_NAME",
        "NamedLakeType": "NAMED_LAKE_LAKE_HAMMAR"
    },
    {
        "Name": "LOC_NAMED_LAKE_LAKE_HAUROKO_NAME",
        "NamedLakeType": "NAMED_LAKE_LAKE_HAUROKO"
    },
    {
        "Name": "LOC_NAMED_LAKE_LAKE_HEVIZ_NAME",
        "NamedLakeType": "NAMED_LAKE_LAKE_HEVIZ"
    },
    {
        "Name": "LOC_NAMED_LAKE_LAKE_HURON_NAME",
        "NamedLakeType": "NAMED_LAKE_LAKE_HURON"
    },
    {
        "Name": "LOC_NAMED_LAKE_LAKE_IDKU_NAME",
        "NamedLakeType": "NAMED_LAKE_LAKE_IDKU"
    },
    {
        "Name": "LOC_NAMED_LAKE_LAKE_INAWASHIRO_NAME",
        "NamedLakeType": "NAMED_LAKE_LAKE_INAWASHIRO"
    },
    {
        "Name": "LOC_NAMED_LAKE_LAKE_ISEO_NAME",
        "NamedLakeType": "NAMED_LAKE_LAKE_ISEO"
    },
    {
        "Name": "LOC_NAMED_LAKE_LAKE_IZNIK_NAME",
        "NamedLakeType": "NAMED_LAKE_LAKE_IZNIK"
    },
    {
        "Name": "LOC_NAMED_LAKE_LAKE_KARLA_NAME",
        "NamedLakeType": "NAMED_LAKE_LAKE_KARLA"
    },
    {
        "Name": "LOC_NAMED_LAKE_LAKE_KASUMIGAURA_NAME",
        "NamedLakeType": "NAMED_LAKE_LAKE_KASUMIGAURA"
    },
    {
        "Name": "LOC_NAMED_LAKE_LAKE_KAWAGUCHI_NAME",
        "NamedLakeType": "NAMED_LAKE_LAKE_KAWAGUCHI"
    },
    {
        "Name": "LOC_NAMED_LAKE_LAKE_KHANKA_NAME",
        "NamedLakeType": "NAMED_LAKE_LAKE_KHANKA"
    },
    {
        "Name": "LOC_NAMED_LAKE_LAKE_KHASAN_NAME",
        "NamedLakeType": "NAMED_LAKE_LAKE_KHASAN"
    },
    {
        "Name": "LOC_NAMED_LAKE_LAKE_KIVU_NAME",
        "NamedLakeType": "NAMED_LAKE_LAKE_KIVU"
    },
    {
        "Name": "LOC_NAMED_LAKE_LAKE_KORONEIA_NAME",
        "NamedLakeType": "NAMED_LAKE_LAKE_KORONEIA"
    },
    {
        "Name": "LOC_NAMED_LAKE_LAKE_KUMMEROW_NAME",
        "NamedLakeType": "NAMED_LAKE_LAKE_KUMMEROW"
    },
    {
        "Name": "LOC_NAMED_LAKE_LAKE_LADOGA_NAME",
        "NamedLakeType": "NAMED_LAKE_LAKE_LADOGA"
    },
    {
        "Name": "LOC_NAMED_LAKE_LAKE_LARIUS_NAME",
        "NamedLakeType": "NAMED_LAKE_LAKE_LARIUS"
    },
    {
        "Name": "LOC_NAMED_LAKE_LAKE_LOUISE_NAME",
        "NamedLakeType": "NAMED_LAKE_LAKE_LOUISE"
    },
    {
        "Name": "LOC_NAMED_LAKE_LAKE_MACKAY_NAME",
        "NamedLakeType": "NAMED_LAKE_LAKE_MACKAY"
    },
    {
        "Name": "LOC_NAMED_LAKE_LAKE_MAI_NDOMBE_NAME",
        "NamedLakeType": "NAMED_LAKE_LAKE_MAI_NDOMBE"
    },
    {
        "Name": "LOC_NAMED_LAKE_LAKE_MAMRY_NAME",
        "NamedLakeType": "NAMED_LAKE_LAKE_MAMRY"
    },
    {
        "Name": "LOC_NAMED_LAKE_LAKE_MANAPOURI_NAME",
        "NamedLakeType": "NAMED_LAKE_LAKE_MANAPOURI"
    },
    {
        "Name": "LOC_NAMED_LAKE_LAKE_MANZALA_NAME",
        "NamedLakeType": "NAMED_LAKE_LAKE_MANZALA"
    },
    {
        "Name": "LOC_NAMED_LAKE_LAKE_MARIOUT_NAME",
        "NamedLakeType": "NAMED_LAKE_LAKE_MARIOUT"
    },
    {
        "Name": "LOC_NAMED_LAKE_LAKE_MARKEN_NAME",
        "NamedLakeType": "NAMED_LAKE_LAKE_MARKEN"
    },
    {
        "Name": "LOC_NAMED_LAKE_LAKE_MATANO_NAME",
        "NamedLakeType": "NAMED_LAKE_LAKE_MATANO"
    },
    {
        "Name": "LOC_NAMED_LAKE_LAKE_MER_WER_NAME",
        "NamedLakeType": "NAMED_LAKE_LAKE_MER_WER"
    },
    {
        "Name": "LOC_NAMED_LAKE_LAKE_MICHIGAN_NAME",
        "NamedLakeType": "NAMED_LAKE_LAKE_MICHIGAN"
    },
    {
        "Name": "LOC_NAMED_LAKE_LAKE_MISTASSINI_NAME",
        "NamedLakeType": "NAMED_LAKE_LAKE_MISTASSINI"
    },
    {
        "Name": "LOC_NAMED_LAKE_LAKE_MURITZ_NAME",
        "NamedLakeType": "NAMED_LAKE_LAKE_MURITZ"
    },
    {
        "Name": "LOC_NAMED_LAKE_LAKE_MWERU_NAME",
        "NamedLakeType": "NAMED_LAKE_LAKE_MWERU"
    },
    {
        "Name": "LOC_NAMED_LAKE_LAKE_NAKAUMI_NAME",
        "NamedLakeType": "NAMED_LAKE_LAKE_NAKAUMI"
    },
    {
        "Name": "LOC_NAMED_LAKE_LAKE_NHLABANE_NAME",
        "NamedLakeType": "NAMED_LAKE_LAKE_NHLABANE"
    },
    {
        "Name": "LOC_NAMED_LAKE_LAKE_NIANGAY_NAME",
        "NamedLakeType": "NAMED_LAKE_LAKE_NIANGAY"
    },
    {
        "Name": "LOC_NAMED_LAKE_LAKE_NICARAGUA_NAME",
        "NamedLakeType": "NAMED_LAKE_LAKE_NICARAGUA"
    },
    {
        "Name": "LOC_NAMED_LAKE_LAKE_NIEGOCIN_NAME",
        "NamedLakeType": "NAMED_LAKE_LAKE_NIEGOCIN"
    },
    {
        "Name": "LOC_NAMED_LAKE_LAKE_NIPIGON_NAME",
        "NamedLakeType": "NAMED_LAKE_LAKE_NIPIGON"
    },
    {
        "Name": "LOC_NAMED_LAKE_LAKE_NYASA_NAME",
        "NamedLakeType": "NAMED_LAKE_LAKE_NYASA"
    },
    {
        "Name": "LOC_NAMED_LAKE_LAKE_OF_BANYOLES_NAME",
        "NamedLakeType": "NAMED_LAKE_LAKE_OF_BANYOLES"
    },
    {
        "Name": "LOC_NAMED_LAKE_LAKE_OF_NAARDEN_NAME",
        "NamedLakeType": "NAMED_LAKE_LAKE_OF_NAARDEN"
    },
    {
        "Name": "LOC_NAMED_LAKE_LAKE_OF_THE_WOODS_NAME",
        "NamedLakeType": "NAMED_LAKE_LAKE_OF_THE_WOODS"
    },
    {
        "Name": "LOC_NAMED_LAKE_LAKE_OKEECHOBEE_NAME",
        "NamedLakeType": "NAMED_LAKE_LAKE_OKEECHOBEE"
    },
    {
        "Name": "LOC_NAMED_LAKE_LAKE_ONEGA_NAME",
        "NamedLakeType": "NAMED_LAKE_LAKE_ONEGA"
    },
    {
        "Name": "LOC_NAMED_LAKE_LAKE_ONTARIO_NAME",
        "NamedLakeType": "NAMED_LAKE_LAKE_ONTARIO"
    },
    {
        "Name": "LOC_NAMED_LAKE_LAKE_PALIASTOMI_NAME",
        "NamedLakeType": "NAMED_LAKE_LAKE_PALIASTOMI"
    },
    {
        "Name": "LOC_NAMED_LAKE_LAKE_PEIPUS_NAME",
        "NamedLakeType": "NAMED_LAKE_LAKE_PEIPUS"
    },
    {
        "Name": "LOC_NAMED_LAKE_LAKE_POSO_NAME",
        "NamedLakeType": "NAMED_LAKE_LAKE_POSO"
    },
    {
        "Name": "LOC_NAMED_LAKE_LAKE_PRESPA_NAME",
        "NamedLakeType": "NAMED_LAKE_LAKE_PRESPA"
    },
    {
        "Name": "LOC_NAMED_LAKE_LAKE_PUKAKI_NAME",
        "NamedLakeType": "NAMED_LAKE_LAKE_PUKAKI"
    },
    {
        "Name": "LOC_NAMED_LAKE_LAKE_PUWPU_NAME",
        "NamedLakeType": "NAMED_LAKE_LAKE_PUWPU"
    },
    {
        "Name": "LOC_NAMED_LAKE_LAKE_ROTOITI_NAME",
        "NamedLakeType": "NAMED_LAKE_LAKE_ROTOITI"
    },
    {
        "Name": "LOC_NAMED_LAKE_LAKE_ROTOMAHANA_NAME",
        "NamedLakeType": "NAMED_LAKE_LAKE_ROTOMAHANA"
    },
    {
        "Name": "LOC_NAMED_LAKE_LAKE_ROTORUA_NAME",
        "NamedLakeType": "NAMED_LAKE_LAKE_ROTORUA"
    },
    {
        "Name": "LOC_NAMED_LAKE_LAKE_SAIMAA_NAME",
        "NamedLakeType": "NAMED_LAKE_LAKE_SAIMAA"
    },
    {
        "Name": "LOC_NAMED_LAKE_LAKE_SAINT_LUCIA_NAME",
        "NamedLakeType": "NAMED_LAKE_LAKE_SAINT_LUCIA"
    },
    {
        "Name": "LOC_NAMED_LAKE_LAKE_SCHWERIN_NAME",
        "NamedLakeType": "NAMED_LAKE_LAKE_SCHWERIN"
    },
    {
        "Name": "LOC_NAMED_LAKE_LAKE_SENTARUM_NAME",
        "NamedLakeType": "NAMED_LAKE_LAKE_SENTARUM"
    },
    {
        "Name": "LOC_NAMED_LAKE_LAKE_SEVAN_NAME",
        "NamedLakeType": "NAMED_LAKE_LAKE_SEVAN"
    },
    {
        "Name": "LOC_NAMED_LAKE_LAKE_SHINJI_NAME",
        "NamedLakeType": "NAMED_LAKE_LAKE_SHINJI"
    },
    {
        "Name": "LOC_NAMED_LAKE_LAKE_SIBHAYI_NAME",
        "NamedLakeType": "NAMED_LAKE_LAKE_SIBHAYI"
    },
    {
        "Name": "LOC_NAMED_LAKE_LAKE_STARNBERG_NAME",
        "NamedLakeType": "NAMED_LAKE_LAKE_STARNBERG"
    },
    {
        "Name": "LOC_NAMED_LAKE_LAKE_SUPERIOR_NAME",
        "NamedLakeType": "NAMED_LAKE_LAKE_SUPERIOR"
    },
    {
        "Name": "LOC_NAMED_LAKE_LAKE_SZELID_NAME",
        "NamedLakeType": "NAMED_LAKE_LAKE_SZELID"
    },
    {
        "Name": "LOC_NAMED_LAKE_LAKE_TAHOE_NAME",
        "NamedLakeType": "NAMED_LAKE_LAKE_TAHOE"
    },
    {
        "Name": "LOC_NAMED_LAKE_LAKE_TAI_NAME",
        "NamedLakeType": "NAMED_LAKE_LAKE_TAI"
    },
    {
        "Name": "LOC_NAMED_LAKE_LAKE_TANA_NAME",
        "NamedLakeType": "NAMED_LAKE_LAKE_TANA"
    },
    {
        "Name": "LOC_NAMED_LAKE_LAKE_TANGANYIKA_NAME",
        "NamedLakeType": "NAMED_LAKE_LAKE_TANGANYIKA"
    },
    {
        "Name": "LOC_NAMED_LAKE_LAKE_TAUPO_NAME",
        "NamedLakeType": "NAMED_LAKE_LAKE_TAUPO"
    },
    {
        "Name": "LOC_NAMED_LAKE_LAKE_TAYMYR_NAME",
        "NamedLakeType": "NAMED_LAKE_LAKE_TAYMYR"
    },
    {
        "Name": "LOC_NAMED_LAKE_LAKE_TE_ANAU_NAME",
        "NamedLakeType": "NAMED_LAKE_LAKE_TE_ANAU"
    },
    {
        "Name": "LOC_NAMED_LAKE_LAKE_TEXCOCO_NAME",
        "NamedLakeType": "NAMED_LAKE_LAKE_TEXCOCO"
    },
    {
        "Name": "LOC_NAMED_LAKE_LAKE_TITIQAQA_NAME",
        "NamedLakeType": "NAMED_LAKE_LAKE_TITIQAQA"
    },
    {
        "Name": "LOC_NAMED_LAKE_LAKE_TOBA_NAME",
        "NamedLakeType": "NAMED_LAKE_LAKE_TOBA"
    },
    {
        "Name": "LOC_NAMED_LAKE_LAKE_TORRENS_NAME",
        "NamedLakeType": "NAMED_LAKE_LAKE_TORRENS"
    },
    {
        "Name": "LOC_NAMED_LAKE_LAKE_TOWUTI_NAME",
        "NamedLakeType": "NAMED_LAKE_LAKE_TOWUTI"
    },
    {
        "Name": "LOC_NAMED_LAKE_LAKE_TRASIMENE_NAME",
        "NamedLakeType": "NAMED_LAKE_LAKE_TRASIMENE"
    },
    {
        "Name": "LOC_NAMED_LAKE_LAKE_TRICHONIDA_NAME",
        "NamedLakeType": "NAMED_LAKE_LAKE_TRICHONIDA"
    },
    {
        "Name": "LOC_NAMED_LAKE_LAKE_TUMBA_NAME",
        "NamedLakeType": "NAMED_LAKE_LAKE_TUMBA"
    },
    {
        "Name": "LOC_NAMED_LAKE_LAKE_TURKANA_NAME",
        "NamedLakeType": "NAMED_LAKE_LAKE_TURKANA"
    },
    {
        "Name": "LOC_NAMED_LAKE_LAKE_TUZ_NAME",
        "NamedLakeType": "NAMED_LAKE_LAKE_TUZ"
    },
    {
        "Name": "LOC_NAMED_LAKE_LAKE_URMIA_NAME",
        "NamedLakeType": "NAMED_LAKE_LAKE_URMIA"
    },
    {
        "Name": "LOC_NAMED_LAKE_LAKE_VAN_NAME",
        "NamedLakeType": "NAMED_LAKE_LAKE_VAN"
    },
    {
        "Name": "LOC_NAMED_LAKE_LAKE_VEGORITIDA_NAME",
        "NamedLakeType": "NAMED_LAKE_LAKE_VEGORITIDA"
    },
    {
        "Name": "LOC_NAMED_LAKE_LAKE_VELENCE_NAME",
        "NamedLakeType": "NAMED_LAKE_LAKE_VELENCE"
    },
    {
        "Name": "LOC_NAMED_LAKE_LAKE_VERBANUS_NAME",
        "NamedLakeType": "NAMED_LAKE_LAKE_VERBANUS"
    },
    {
        "Name": "LOC_NAMED_LAKE_LAKE_VICTORIA_NAME",
        "NamedLakeType": "NAMED_LAKE_LAKE_VICTORIA"
    },
    {
        "Name": "LOC_NAMED_LAKE_LAKE_VISTONIDA_NAME",
        "NamedLakeType": "NAMED_LAKE_LAKE_VISTONIDA"
    },
    {
        "Name": "LOC_NAMED_LAKE_LAKE_VOLVI_NAME",
        "NamedLakeType": "NAMED_LAKE_LAKE_VOLVI"
    },
    {
        "Name": "LOC_NAMED_LAKE_LAKE_WAIKAREMOANA_NAME",
        "NamedLakeType": "NAMED_LAKE_LAKE_WAIKAREMOANA"
    },
    {
        "Name": "LOC_NAMED_LAKE_LAKE_WAKATIPU_NAME",
        "NamedLakeType": "NAMED_LAKE_LAKE_WAKATIPU"
    },
    {
        "Name": "LOC_NAMED_LAKE_LAKE_WALCHEN_NAME",
        "NamedLakeType": "NAMED_LAKE_LAKE_WALCHEN"
    },
    {
        "Name": "LOC_NAMED_LAKE_LAKE_WANAKA_NAME",
        "NamedLakeType": "NAMED_LAKE_LAKE_WANAKA"
    },
    {
        "Name": "LOC_NAMED_LAKE_LAKE_WIGRY_NAME",
        "NamedLakeType": "NAMED_LAKE_LAKE_WIGRY"
    },
    {
        "Name": "LOC_NAMED_LAKE_LAKE_WINDERMERE_NAME",
        "NamedLakeType": "NAMED_LAKE_LAKE_WINDERMERE"
    },
    {
        "Name": "LOC_NAMED_LAKE_LAKE_WINNEBAGO_NAME",
        "NamedLakeType": "NAMED_LAKE_LAKE_WINNEBAGO"
    },
    {
        "Name": "LOC_NAMED_LAKE_LAKE_WINNIPEG_NAME",
        "NamedLakeType": "NAMED_LAKE_LAKE_WINNIPEG"
    },
    {
        "Name": "LOC_NAMED_LAKE_LAKE_WINNIPEGOSIS_NAME",
        "NamedLakeType": "NAMED_LAKE_LAKE_WINNIPEGOSIS"
    },
    {
        "Name": "LOC_NAMED_LAKE_LAKE_XALTOCAN_NAME",
        "NamedLakeType": "NAMED_LAKE_LAKE_XALTOCAN"
    },
    {
        "Name": "LOC_NAMED_LAKE_LAKE_XOCHIMILCO_NAME",
        "NamedLakeType": "NAMED_LAKE_LAKE_XOCHIMILCO"
    },
    {
        "Name": "LOC_NAMED_LAKE_LAKE_YEAK_LAOM_NAME",
        "NamedLakeType": "NAMED_LAKE_LAKE_YEAK_LAOM"
    },
    {
        "Name": "LOC_NAMED_LAKE_LAKE_ZUMPANGO_NAME",
        "NamedLakeType": "NAMED_LAKE_LAKE_ZUMPANGO"
    },
    {
        "Name": "LOC_NAMED_LAKE_LAKE_IJSSEL_NAME",
        "NamedLakeType": "NAMED_LAKE_LAKE_IJSSEL"
    },
    {
        "Name": "LOC_NAMED_LAKE_LAUWERS_LAKE_NAME",
        "NamedLakeType": "NAMED_LAKE_LAUWERS_LAKE"
    },
    {
        "Name": "LOC_NAMED_LAKE_LIMINGEN_NAME",
        "NamedLakeType": "NAMED_LAKE_LIMINGEN"
    },
    {
        "Name": "LOC_NAMED_LAKE_LOCH_AWE_NAME",
        "NamedLakeType": "NAMED_LAKE_LOCH_AWE"
    },
    {
        "Name": "LOC_NAMED_LAKE_LOCH_CORUISK_NAME",
        "NamedLakeType": "NAMED_LAKE_LOCH_CORUISK"
    },
    {
        "Name": "LOC_NAMED_LAKE_LOCH_FINLAGGAN_NAME",
        "NamedLakeType": "NAMED_LAKE_LOCH_FINLAGGAN"
    },
    {
        "Name": "LOC_NAMED_LAKE_LOCH_LOMOND_NAME",
        "NamedLakeType": "NAMED_LAKE_LOCH_LOMOND"
    },
    {
        "Name": "LOC_NAMED_LAKE_LOCH_MAREE_NAME",
        "NamedLakeType": "NAMED_LAKE_LOCH_MAREE"
    },
    {
        "Name": "LOC_NAMED_LAKE_LOCH_MORAR_NAME",
        "NamedLakeType": "NAMED_LAKE_LOCH_MORAR"
    },
    {
        "Name": "LOC_NAMED_LAKE_LOCH_NESS_NAME",
        "NamedLakeType": "NAMED_LAKE_LOCH_NESS"
    },
    {
        "Name": "LOC_NAMED_LAKE_LOCH_TAY_NAME",
        "NamedLakeType": "NAMED_LAKE_LOCH_TAY"
    },
    {
        "Name": "LOC_NAMED_LAKE_LOKTAK_LAKE_NAME",
        "NamedLakeType": "NAMED_LAKE_LOKTAK_LAKE"
    },
    {
        "Name": "LOC_NAMED_LAKE_LUKNAJNO_LAKE_NAME",
        "NamedLakeType": "NAMED_LAKE_LUKNAJNO_LAKE"
    },
    {
        "Name": "LOC_NAMED_LAKE_MAHARLOO_LAKE_NAME",
        "NamedLakeType": "NAMED_LAKE_MAHARLOO_LAKE"
    },
    {
        "Name": "LOC_NAMED_LAKE_MALAREN_NAME",
        "NamedLakeType": "NAMED_LAKE_MALAREN"
    },
    {
        "Name": "LOC_NAMED_LAKE_MALLALAFQUEN_NAME",
        "NamedLakeType": "NAMED_LAKE_MALLALAFQUEN"
    },
    {
        "Name": "LOC_NAMED_LAKE_MJOSA_NAME",
        "NamedLakeType": "NAMED_LAKE_MJOSA"
    },
    {
        "Name": "LOC_NAMED_LAKE_MOSVATNET_NAME",
        "NamedLakeType": "NAMED_LAKE_MOSVATNET "
    },
    {
        "Name": "LOC_NAMED_LAKE_MUNDAU_LAGOON_NAME",
        "NamedLakeType": "NAMED_LAKE_MUNDAU_LAGOON"
    },
    {
        "Name": "LOC_NAMED_LAKE_NAMAK_LAKE_NAME",
        "NamedLakeType": "NAMED_LAKE_NAMAK_LAKE"
    },
    {
        "Name": "LOC_NAMED_LAKE_NISSER_NAME",
        "NamedLakeType": "NAMED_LAKE_NISSER"
    },
    {
        "Name": "LOC_NAMED_LAKE_NORSJO_NAME",
        "NamedLakeType": "NAMED_LAKE_NORSJO"
    },
    {
        "Name": "LOC_NAMED_LAKE_ORETI_LAKE_NAME",
        "NamedLakeType": "NAMED_LAKE_ORETI_LAKE"
    },
    {
        "Name": "LOC_NAMED_LAKE_OROS_LAKE_NAME",
        "NamedLakeType": "NAMED_LAKE_OROS_LAKE"
    },
    {
        "Name": "LOC_NAMED_LAKE_OYEREN_NAME",
        "NamedLakeType": "NAMED_LAKE_OYEREN"
    },
    {
        "Name": "LOC_NAMED_LAKE_PALLQAQUCHA_NAME",
        "NamedLakeType": "NAMED_LAKE_PALLQAQUCHA"
    },
    {
        "Name": "LOC_NAMED_LAKE_PANGONG_TSO_NAME",
        "NamedLakeType": "NAMED_LAKE_PANGONG_TSO"
    },
    {
        "Name": "LOC_NAMED_LAKE_PARAVANI_LAKE_NAME",
        "NamedLakeType": "NAMED_LAKE_PARAVANI_LAKE"
    },
    {
        "Name": "LOC_NAMED_LAKE_PARIWANAQUCHA_NAME",
        "NamedLakeType": "NAMED_LAKE_PARIWANAQUCHA"
    },
    {
        "Name": "LOC_NAMED_LAKE_PLAUER_SEE_NAME",
        "NamedLakeType": "NAMED_LAKE_PLAUER_SEE"
    },
    {
        "Name": "LOC_NAMED_LAKE_POYANG_LAKE_NAME",
        "NamedLakeType": "NAMED_LAKE_POYANG_LAKE"
    },
    {
        "Name": "LOC_NAMED_LAKE_QINGHAI_LAKE_NAME",
        "NamedLakeType": "NAMED_LAKE_QINGHAI_LAKE"
    },
    {
        "Name": "LOC_NAMED_LAKE_REINDEER_LAKE_NAME",
        "NamedLakeType": "NAMED_LAKE_REINDEER_LAKE"
    },
    {
        "Name": "LOC_NAMED_LAKE_REPRESA_DE_ENG_SOUZA_DIAS_NAME",
        "NamedLakeType": "NAMED_LAKE_REPRESA_DE_ENG_SOUZA_DIAS"
    },
    {
        "Name": "LOC_NAMED_LAKE_RINIHUE_LAKE_NAME",
        "NamedLakeType": "NAMED_LAKE_RINIHUE_LAKE"
    },
    {
        "Name": "LOC_NAMED_LAKE_ROSSVATNET_NAME",
        "NamedLakeType": "NAMED_LAKE_ROSSVATNET"
    },
    {
        "Name": "LOC_NAMED_LAKE_SAALER_BODDEN_NAME",
        "NamedLakeType": "NAMED_LAKE_SAALER_BODDEN"
    },
    {
        "Name": "LOC_NAMED_LAKE_SAMJI_LAKE_NAME",
        "NamedLakeType": "NAMED_LAKE_SAMJI_LAKE"
    },
    {
        "Name": "LOC_NAMED_LAKE_SANABRIA_LAKE_NAME",
        "NamedLakeType": "NAMED_LAKE_SANABRIA_LAKE"
    },
    {
        "Name": "LOC_NAMED_LAKE_SARYGAMYSH_LAKE_NAME",
        "NamedLakeType": "NAMED_LAKE_SARYGAMYSH_LAKE"
    },
    {
        "Name": "LOC_NAMED_LAKE_SCHAALSEE_NAME",
        "NamedLakeType": "NAMED_LAKE_SCHAALSEE"
    },
    {
        "Name": "LOC_NAMED_LAKE_SEA_OF_GALILEE_NAME",
        "NamedLakeType": "NAMED_LAKE_SEA_OF_GALILEE"
    },
    {
        "Name": "LOC_NAMED_LAKE_SELBUSJOEN_NAME",
        "NamedLakeType": "NAMED_LAKE_SELBUSJOEN"
    },
    {
        "Name": "LOC_NAMED_LAKE_SHUSWAP_LAKE_NAME",
        "NamedLakeType": "NAMED_LAKE_SHUSWAP_LAKE"
    },
    {
        "Name": "LOC_NAMED_LAKE_SNASAVATNET_NAME",
        "NamedLakeType": "NAMED_LAKE_SNASAVATNET"
    },
    {
        "Name": "LOC_NAMED_LAKE_SNIARDWY_NAME",
        "NamedLakeType": "NAMED_LAKE_SNIARDWY"
    },
    {
        "Name": "LOC_NAMED_LAKE_STEINHUDER_MEER_NAME",
        "NamedLakeType": "NAMED_LAKE_STEINHUDER_MEER"
    },
    {
        "Name": "LOC_NAMED_LAKE_STORSJON_NAME",
        "NamedLakeType": "NAMED_LAKE_STORSJON"
    },
    {
        "Name": "LOC_NAMED_LAKE_TABATSKURI_LAKE_NAME",
        "NamedLakeType": "NAMED_LAKE_TABATSKURI_LAKE"
    },
    {
        "Name": "LOC_NAMED_LAKE_TE_WAIHORA_NAME",
        "NamedLakeType": "NAMED_LAKE_TE_WAIHORA"
    },
    {
        "Name": "LOC_NAMED_LAKE_TINNSJOEN_NAME",
        "NamedLakeType": "NAMED_LAKE_TINNSJOEN"
    },
    {
        "Name": "LOC_NAMED_LAKE_TONLE_BATI_LAKE_NAME",
        "NamedLakeType": "NAMED_LAKE_TONLE_BATI_LAKE"
    },
    {
        "Name": "LOC_NAMED_LAKE_TONLE_SAP_NAME",
        "NamedLakeType": "NAMED_LAKE_TONLE_SAP"
    },
    {
        "Name": "LOC_NAMED_LAKE_TYRIFJORDEN_NAME",
        "NamedLakeType": "NAMED_LAKE_TYRIFJORDEN"
    },
    {
        "Name": "LOC_NAMED_LAKE_ULLSWATER_LAKE_NAME",
        "NamedLakeType": "NAMED_LAKE_ULLSWATER_LAKE"
    },
    {
        "Name": "LOC_NAMED_LAKE_UTIKUMA_LAKE_NAME",
        "NamedLakeType": "NAMED_LAKE_UTIKUMA_LAKE"
    },
    {
        "Name": "LOC_NAMED_LAKE_UVS_LAKE_NAME",
        "NamedLakeType": "NAMED_LAKE_UVS_LAKE"
    },
    {
        "Name": "LOC_NAMED_LAKE_VANERN_NAME",
        "NamedLakeType": "NAMED_LAKE_VANERN"
    },
    {
        "Name": "LOC_NAMED_LAKE_VATTERN_NAME",
        "NamedLakeType": "NAMED_LAKE_VATTERN"
    },
    {
        "Name": "LOC_NAMED_LAKE_VEMBANAD_LAKE_NAME",
        "NamedLakeType": "NAMED_LAKE_VEMBANAD_LAKE"
    },
    {
        "Name": "LOC_NAMED_LAKE_WABAMUN_LAKE_NAME",
        "NamedLakeType": "NAMED_LAKE_WABAMUN_LAKE"
    },
    {
        "Name": "LOC_NAMED_LAKE_WAKAW_LAKE_NAME",
        "NamedLakeType": "NAMED_LAKE_WAKAW_LAKE"
    },
    {
        "Name": "LOC_NAMED_LAKE_WASKESIU_LAKE_NAME",
        "NamedLakeType": "NAMED_LAKE_WASKESIU_LAKE"
    },
    {
        "Name": "LOC_NAMED_LAKE_WEST_LAKE_NAME",
        "NamedLakeType": "NAMED_LAKE_WEST_LAKE"
    },
    {
        "Name": "LOC_NAMED_LAKE_WEST_NUBIAN_LAKE_NAME",
        "NamedLakeType": "NAMED_LAKE_WEST_NUBIAN_LAKE"
    },
    {
        "Name": "LOC_NAMED_LAKE_WOJNOWO_LAKE_NAME",
        "NamedLakeType": "NAMED_LAKE_WOJNOWO_LAKE"
    },
    {
        "Name": "LOC_NAMED_LAKE_WOLLASTON_LAKE_NAME",
        "NamedLakeType": "NAMED_LAKE_WOLLASTON_LAKE"
    },
    {
        "Name": "LOC_NAMED_LAKE_YANAQUCHA_NAME",
        "NamedLakeType": "NAMED_LAKE_YANAQUCHA"
    },
    {
        "Name": "LOC_NAMED_LAKE_LAKE_IZABAL_NAME",
        "NamedLakeType": "NAMED_LAKE_LAKE_IZABAL"
    },
    {
        "Name": "LOC_NAMED_LAKE_LAKE_PETEN_ITZA_NAME",
        "NamedLakeType": "NAMED_LAKE_LAKE_PETEN_ITZA"
    },
    {
        "Name": "LOC_NAMED_LAKE_LAKE_AMATITLAN_NAME",
        "NamedLakeType": "NAMED_LAKE_LAKE_AMATITLAN"
    },
    {
        "Name": "LOC_NAMED_LAKE_LAKE_GUIJA_NAME",
        "NamedLakeType": "NAMED_LAKE_LAKE_GUIJA"
    },
    {
        "Name": "LOC_NAMED_LAKE_LAKE_LEOPOLDO_NAME",
        "NamedLakeType": "NAMED_LAKE_LAKE_LEOPOLDO"
    },
    {
        "Name": "LOC_NAMED_LAKE_LAKE_VALENCIA_NAME",
        "NamedLakeType": "NAMED_LAKE_LAKE_VALENCIA"
    },
    {
        "Name": "LOC_NAMED_LAKE_LAKE_TOTA_NAME",
        "NamedLakeType": "NAMED_LAKE_LAKE_TOTA"
    },
    {
        "Name": "LOC_NAMED_LAKE_LAGUNA_DE_LA_COCHA_NAME",
        "NamedLakeType": "NAMED_LAKE_LAGUNA_DE_LA_COCHA"
    },
    {
        "Name": "LOC_NAMED_LAKE_LAKE_HERRERA_NAME",
        "NamedLakeType": "NAMED_LAKE_LAKE_HERRERA"
    },
    {
        "Name": "LOC_NAMED_LAKE_LAKE_NEUCHATEL_NAME",
        "NamedLakeType": "NAMED_LAKE_LAKE_NEUCHATEL"
    },
    {
        "Name": "LOC_NAMED_LAKE_BA_BE_LAKE_NAME",
        "NamedLakeType": "NAMED_LAKE_BA_BE_LAKE"
    },
    {
        "Name": "LOC_NAMED_LAKE_HO_TAY_NAME",
        "NamedLakeType": "NAMED_LAKE_HO_TAY"
    },
    {
        "Name": "LOC_NAMED_LAKE_LAK_LAKE_NAME",
        "NamedLakeType": "NAMED_LAKE_LAK_LAKE"
    },
    {
        "Name": "LOC_NAMED_LAKE_LAKE_ABAYA_NAME",
        "NamedLakeType": "NAMED_LAKE_LAKE_ABAYA"
    },
    {
        "Name": "LOC_NAMED_LAKE_LAKE_ZIWAY_NAME",
        "NamedLakeType": "NAMED_LAKE_LAKE_ZIWAY"
    },
    {
        "Name": "LOC_NAMED_LAKE_LAKE_CHAMO_NAME",
        "NamedLakeType": "NAMED_LAKE_LAKE_CHAMO"
    },
    {
        "Name": "LOC_NAMED_LAKE_LAKE_SHALA_NAME",
        "NamedLakeType": "NAMED_LAKE_LAKE_SHALA"
    },
    {
        "Name": "LOC_NAMED_LAKE_LAKE_CHEW_BAHIR_NAME",
        "NamedLakeType": "NAMED_LAKE_LAKE_CHEW_BAHIR"
    },
    {
        "Name": "LOC_NAMED_LAKE_LAKE_ABBE_NAME",
        "NamedLakeType": "NAMED_LAKE_LAKE_ABBE"
    },
    {
        "Name": "LOC_NAMED_LAKE_LAGOA_DO_FOGO_NAME",
        "NamedLakeType": "NAMED_LAKE_LAGOA_DO_FOGO"
    },
    {
        "Name": "LOC_NAMED_LAKE_LAGOA_DAS_SETE_CIDADES_NAME",
        "NamedLakeType": "NAMED_LAKE_LAGOA_DAS_SETE_CIDADES"
    },
    {
        "Name": "LOC_NAMED_LAKE_LAGOA_DAS_FURNAS_NAME",
        "NamedLakeType": "NAMED_LAKE_LAGOA_DAS_FURNAS"
    },
    {
        "Name": "LOC_NAMED_LAKE_LAGOA_DE_SANTIAGO_NAME",
        "NamedLakeType": "NAMED_LAKE_LAGOA_DE_SANTIAGO"
    },
    {
        "Name": "LOC_NAMED_LAKE_LAGOAS_DE_BERTIANDOS_NAME",
        "NamedLakeType": "NAMED_LAKE_LAGOAS_DE_BERTIANDOS"
    },
    {
        "Name": "LOC_NAMED_LAKE_PATEIRA_DE_FERMENTELOS_NAME",
        "NamedLakeType": "NAMED_LAKE_PATEIRA_DE_FERMENTELOS"
    },
    {
        "Name": "LOC_NAMED_LAKE_LAGOA_DA_VELA_NAME",
        "NamedLakeType": "NAMED_LAKE_LAGOA_DA_VELA"
    }
]