[
    {
        "Description": "LOC_GOODYHUT_CULTURE_GRANT_CIVIC",
        "GoodyHut": "GOODYHUT_CULTURE",
        "Heal": 0,
        "MinOneCity": 0,
        "ModifierID": "GOODY_CULTURE_GRANT_FULL_CIVIC",
        "NearestCityNaval": 0,
        "RequiresCityGreatWorkObjectType": null,
        "RequiresUnit": 0,
        "SubTypeGoodyHut": "GOODYHUT_FULL_CIVIC",
        "Turn": 30,
        "UpgradeUnit": 0,
        "Weight": 30
    },
    {
        "Description": "LOC_GOODYHUT_CULTURE_GRANT_BOOST",
        "GoodyHut": "GOODYHUT_CULTURE",
        "Heal": 0,
        "MinOneCity": 0,
        "ModifierID": "GOODY_CULTURE_GRANT_ONE_CIVIC_BOOST",
        "NearestCityNaval": 0,
        "RequiresCityGreatWorkObjectType": null,
        "RequiresUnit": 0,
        "SubTypeGoodyHut": "GOODYHUT_ONE_CIVIC_BOOST",
        "Turn": 0,
        "UpgradeUnit": 0,
        "Weight": 50
    },
    {
        "Description": "LOC_GOODYHUT_LARGE_GOLD_DESCRIPTION",
        "GoodyHut": "GOODYHUT_GOLD",
        "Heal": 0,
        "MinOneCity": 1,
        "ModifierID": "GOODY_GOLD_LARGE_MODIFIER",
        "NearestCityNaval": 0,
        "RequiresCityGreatWorkObjectType": null,
        "RequiresUnit": 0,
        "SubTypeGoodyHut": "GOODYHUT_LARGE_GOLD",
        "Turn": 40,
        "UpgradeUnit": 0,
        "Weight": 15
    },
    {
        "Description": "LOC_GOODYHUT_MEDIUM_GOLD_DESCRIPTION",
        "GoodyHut": "GOODYHUT_GOLD",
        "Heal": 0,
        "MinOneCity": 1,
        "ModifierID": "GOODY_GOLD_MEDIUM_MODIFIER",
        "NearestCityNaval": 0,
        "RequiresCityGreatWorkObjectType": null,
        "RequiresUnit": 0,
        "SubTypeGoodyHut": "GOODYHUT_MEDIUM_GOLD",
        "Turn": 20,
        "UpgradeUnit": 0,
        "Weight": 30
    },
    {
        "Description": "LOC_GOODYHUT_SMALL_GOLD_DESCRIPTION",
        "GoodyHut": "GOODYHUT_GOLD",
        "Heal": 0,
        "MinOneCity": 1,
        "ModifierID": "GOODY_GOLD_SMALL_MODIFIER",
        "NearestCityNaval": 0,
        "RequiresCityGreatWorkObjectType": null,
        "RequiresUnit": 0,
        "SubTypeGoodyHut": "GOODYHUT_SMALL_GOLD",
        "Turn": 0,
        "UpgradeUnit": 0,
        "Weight": 55
    },
    {
        "Description": "LOC_GOODYHUT_LARGE_HAPPINESS_DESCRIPTION",
        "GoodyHut": "GOODYHUT_HAPPINESS",
        "Heal": 0,
        "MinOneCity": 1,
        "ModifierID": "GOODY_HAPPINESS_LARGE_MODIFIER",
        "NearestCityNaval": 0,
        "RequiresCityGreatWorkObjectType": null,
        "RequiresUnit": 0,
        "SubTypeGoodyHut": "GOODYHUT_LARGE_HAPPINESS",
        "Turn": 40,
        "UpgradeUnit": 0,
        "Weight": 15
    },
    {
        "Description": "LOC_GOODYHUT_MEDIUM_HAPPINESS_DESCRIPTION",
        "GoodyHut": "GOODYHUT_HAPPINESS",
        "Heal": 0,
        "MinOneCity": 1,
        "ModifierID": "GOODY_HAPPINESS_MEDIUM_MODIFIER",
        "NearestCityNaval": 0,
        "RequiresCityGreatWorkObjectType": null,
        "RequiresUnit": 0,
        "SubTypeGoodyHut": "GOODYHUT_MEDIUM_HAPPINESS",
        "Turn": 20,
        "UpgradeUnit": 0,
        "Weight": 30
    },
    {
        "Description": "LOC_GOODYHUT_SMALL_HAPPINESS_DESCRIPTION",
        "GoodyHut": "GOODYHUT_HAPPINESS",
        "Heal": 0,
        "MinOneCity": 1,
        "ModifierID": "GOODY_HAPPINESS_SMALL_MODIFIER",
        "NearestCityNaval": 0,
        "RequiresCityGreatWorkObjectType": null,
        "RequiresUnit": 0,
        "SubTypeGoodyHut": "GOODYHUT_SMALL_HAPPINESS",
        "Turn": 0,
        "UpgradeUnit": 0,
        "Weight": 55
    },
    {
        "Description": "LOC_GOODYHUT_MILITARY_GRANT_LAND_UNIT_DESCRIPTION",
        "GoodyHut": "GOODYHUT_MILITARY",
        "Heal": 0,
        "MinOneCity": 1,
        "ModifierID": "GOODY_MILITARY_GRANT_LAND_UNIT",
        "NearestCityNaval": 0,
        "RequiresCityGreatWorkObjectType": null,
        "RequiresUnit": 0,
        "SubTypeGoodyHut": "GOODYHUT_GRANT_LAND_UNIT",
        "Turn": 0,
        "UpgradeUnit": 0,
        "Weight": 50
    },
    {
        "Description": "LOC_GOODYHUT_MILITARY_GRANT_NAVAL_UNIT_DESCRIPTION",
        "GoodyHut": "GOODYHUT_MILITARY",
        "Heal": 0,
        "MinOneCity": 1,
        "ModifierID": "GOODY_MILITARY_GRANT_NAVAL_UNIT",
        "NearestCityNaval": 1,
        "RequiresCityGreatWorkObjectType": null,
        "RequiresUnit": 0,
        "SubTypeGoodyHut": "GOODYHUT_GRANT_NAVAL_UNIT",
        "Turn": 0,
        "UpgradeUnit": 0,
        "Weight": 30
    },
    {
        "Description": "LOC_GOODYHUT_SCIENCE_GRANT_TECH",
        "GoodyHut": "GOODYHUT_SCIENCE",
        "Heal": 0,
        "MinOneCity": 0,
        "ModifierID": "GOODY_SCIENCE_GRANT_FULL_TECH",
        "NearestCityNaval": 0,
        "RequiresCityGreatWorkObjectType": null,
        "RequiresUnit": 0,
        "SubTypeGoodyHut": "GOODYHUT_FULL_TECH",
        "Turn": 30,
        "UpgradeUnit": 0,
        "Weight": 30
    },
    {
        "Description": "LOC_GOODYHUT_SCIENCE_GRANT_BOOST",
        "GoodyHut": "GOODYHUT_SCIENCE",
        "Heal": 0,
        "MinOneCity": 0,
        "ModifierID": "GOODY_SCIENCE_GRANT_ONE_TECH_BOOST",
        "NearestCityNaval": 0,
        "RequiresCityGreatWorkObjectType": null,
        "RequiresUnit": 0,
        "SubTypeGoodyHut": "GOODYHUT_ONE_TECH_BOOST",
        "Turn": 0,
        "UpgradeUnit": 0,
        "Weight": 50
    },
    {
        "Description": "LOC_GOODYHUT_SCIENCE_GRANT_ONE_CODEX_DESCRIPTION",
        "GoodyHut": "GOODYHUT_SCIENCE",
        "Heal": 0,
        "MinOneCity": 0,
        "ModifierID": "GOODY_SCIENCE_GRANT_ONE_CODEX",
        "NearestCityNaval": 0,
        "RequiresCityGreatWorkObjectType": "GREATWORKOBJECT_WRITING",
        "RequiresUnit": 0,
        "SubTypeGoodyHut": "GOODY_SCIENCE_GRANT_ONE_CODEX",
        "Turn": 0,
        "UpgradeUnit": 0,
        "Weight": 20
    },
    {
        "Description": "LOC_GOODYHUT_SURVIVORS_GRANT_MIGRANT_DESCRIPTION",
        "GoodyHut": "GOODYHUT_SURVIVORS",
        "Heal": 0,
        "MinOneCity": 1,
        "ModifierID": "GOODY_SURVIVORS_GRANT_MIGRANT",
        "NearestCityNaval": 0,
        "RequiresCityGreatWorkObjectType": null,
        "RequiresUnit": 0,
        "SubTypeGoodyHut": "GOODYHUT_GRANT_MIGRANT",
        "Turn": 0,
        "UpgradeUnit": 0,
        "Weight": 0
    },
    {
        "Description": "LOC_GOODYHUT_SURVIVORS_GRANT_COMMANDER_DESCRIPTION",
        "GoodyHut": "GOODYHUT_SURVIVORS",
        "Heal": 0,
        "MinOneCity": 1,
        "ModifierID": "GOODY_SURVIVORS_GRANT_COMMANDER",
        "NearestCityNaval": 0,
        "RequiresCityGreatWorkObjectType": null,
        "RequiresUnit": 0,
        "SubTypeGoodyHut": "GOODYHUT_GRANT_COMMANDER",
        "Turn": 15,
        "UpgradeUnit": 0,
        "Weight": 40
    },
    {
        "Description": "LOC_GOODYHUT_SURVIVORS_GRANT_SCOUT_DESCRIPTION",
        "GoodyHut": "GOODYHUT_SURVIVORS",
        "Heal": 0,
        "MinOneCity": 1,
        "ModifierID": "GOODY_SURVIVORS_GRANT_SCOUT",
        "NearestCityNaval": 0,
        "RequiresCityGreatWorkObjectType": null,
        "RequiresUnit": 0,
        "SubTypeGoodyHut": "GOODYHUT_GRANT_SCOUT",
        "Turn": 0,
        "UpgradeUnit": 0,
        "Weight": 60
    }
]